### 一.基础知识：二进制
    1.二进制、八进制、十进制、十六进制的转换
    2.原码、反码、补码；负数的二进制、十进制的转换
    3.位运算：& |  ~  ^  >>  <<  >>>
    4.长整数、短整数
    5.大小端 big/little endia

### 二.JVM基本概念+ClassFileFormat
    1.JVM是一种规范
        JVM：字节码指令集；内存管理（堆、栈、方法区）
        JVM：从跨平台的语言到跨语言的平台
    2.常见的JVM
    3.字节码文件格式
        查看16进制的.class文件:notepad
        查看ByteCode（字节码文件）:JClassLib;javap -v class文件路径
    
        magic 
        minor version
        major version
        constant pool count、constant pool
        access flag
        this class
        super class
        interface count 、interfaces
        fields count、fields
        methods count 、method info
        attribute count 、attribute
### 三、类加载Loading
    1.类加载器
        bootstrap、Extension App Customer
    2.双亲委派过程
        主要出于安全来考虑
        java.lang.String不能用自定义的类加载器进行加载
        异常：ClassNotFoundException
    3.类加载范围
        sun.boot.class.class
        java.ext.dirs
        java.class.path
    4.launcher
        ClassLoader的包装类
        三个加载器是Launcher的内部类，类中指定了加载范围（加载类的路径）
    5.lazyLoading的五种情况（面试题）
        JVM规范并没有规定什么时候进行加载，但是规定了什么时候必须初始化
        其实严格来说应该是Lazy initialing
        
        new，getStatic、putStatic、invoiceStatic指令，访问final除外
        java.lang.reflect对类进行反射调用
        初始化子类的时候，父类必须初始化
        虚拟机启动的时候，被执行的主类必须初始化
        动态语言支持java.lang.invoke.MethodHandle解析的结果为REF_getstatic、REF_putstatic、REF_invokestatic的方法句柄时，该类必须初始化
        
    6.classLoader源码
        findInCache--parent.loadClass--findClass
        自定义ClassLoader：实现findClass方法就可以
        迭代
        使用的设计模式：钩子函数、模板方法（ClassLoader loadClass的时候）
        loadClass是将加载到内存的中的类对象返回
    7.自定义类加载器
        如何实现：
            1.extends ClassLoader 
            2.override findClass -> defineClass(bytes[] -> Class claszz)
            3.最后记得 return super.findClass(classname);
            
        应用：1.利用类加载加载一些资源，可以对这些资源进行加密
            *代码手撕*
            用的技术：读文件、写文件、加密
        
        ClassLoader跟反射的关系：ClassLoader是反射的基石，ClassLoader获取的class对象，再进行反射
        
        什么时候需要加载一个类？Spring的动态代理；JRebel热部署
        
        tomcat、spring都定义了自己的ClassLoader
    
    8.获取ClassLoader的parent（源码）
        ClassLoader的构造方法 -> getSystemClassLoader -> initSystemClassLoader(通过launcher获取ClassLoader)
        
        launcher的构造方法：指定了APP为默认的ClassLoader
        
    9.双亲委派机制的打破（面试题）
        如何打破：重写loadClass方法
        何时打破：
            1. JDK1.2之前，自定义ClassLoader需要重写loadClass方法
            2. ThreadContextClassLoader可以实现基类调用实现类的代码，通过thread.setContextClassLoader指定
            3.热启动、热部署
                osgi、tomcat都有自己的模块指定classLoader（可以加载同一类库的不同版本）
                
                tomcat热部署，因为tomcat重写了classLoader，热部署的时候会将之前的classLoader干掉，再重新new一个classLoader
    
    10.混合模式
        面试题：JVM为什么不直接编译呢？：启动慢；现在解释器执行很快
        
        解释器：bytecode intepreter
        JIT: just in-time compiler
        
        通过命令设置模式: -Xmixed   -Xint(启动快，执行慢)   -Xcomp（启动慢，执行快）

        热点代码检测：
            多次被调用的方法（方法计数器）
            多次被调用的循环（循环计数器）
         检测热点代码：-XX:CompileThreshold=10000
                
### 四、类初始化
    2.Linking
        1.verification
            验证文件是否符合JVM规范
        2.preparation（面试常考）
            静态成员变量赋默认值
        3.resolution
            类、属性、方法等符号引用解析为直接引用
            常量池中的各种符号引用解析为指针、偏移量等内存地址的直接引用
    
    3.initializing
        调用类初始化代码<cinit>,静态成员变量赋初始值
        
    区别：
        load类：默认值，初始值
            静态变量是类加载过程中分为两步，preparation 和initializing
            面试题：T001_ClassLoadingProcedure，代码执行结果
            
        new对象：申请内存，默认值，初始值
            new 对象是：1.先分配内存，成员变量赋默认值；2.构造方法，赋值为初始值
        
    单例模式的DCL，INSTANCE需要加volatile，防止指令重排  
        INSTANCE = new Mgr06();  
        new对象分两步，在第一步赋默认值后被别的线程读取，在没有赋初始值之前，从默认值开始进行count++
        
### 五、对象内存布局
    1.请解释一下对象的创建过程
        类加载【loading、linking（verification、preparation、resolution）、initializing】
        对象创建（申请内存，成员变量赋默认值；执行构造方法，成员变量赋初始值）
            通过二进制指令来分析
            new  dup  invokespecial <init>
            通过二进制指令来理解乱序，指令重排序；以及DDL单例模式的双重检查，
            
    2.对象在内存中的存储布局
        普通对象：对象头、类型指针、实例数据、对齐
        数组：对象头、类型指针、数组长度、实例数据、对齐
        
    3.对象头具体包含什么？
        hotspot：64位
            无锁态：锁标志位(2)、偏向锁位（1）、分代年龄（4）、hashcode（31）
            偏向锁：锁标志位(2)、偏向锁位（1）、分代年龄（4）、当前线程的指针（54）
            轻量级锁：锁标志位(2)、、指向线程栈中local record的指针（62）
            重量级锁：锁标志位(2)、、指向互斥锁的指针（62）
            GC标记信息：锁标志位(2)、CMS过程中用到的标记信息（62）
            
        hotspot：32位：
            无锁态：锁标志位(2)、偏向锁位（1）、分代年龄（4）、hashcode（25）
            偏向锁：锁标志位(2)、偏向锁位（1）、分代年龄（4）、线程id（23）、Epoch（2）
            轻量级锁：锁标志位(2)、指向线程栈中local record的指针（30）
            重量级锁：锁标志位(2)、指向互斥锁的指针（30）
            GC标记信息：锁标志位(2)、空（30）
        
    4.对象如何定位
        句柄池(间接指针、三色标记时效率高)、直接指针（hotspot采用）
        两种无优劣之分
        
    5.对象如何分配？
        对象分配过程如下：start会new一个新的对象，
        首先在栈上分配，如果能分配就会分配到栈上，栈上有个好处就是直接往里一弹搞定，弹出来之后结束。
        如果分配不了，就会判断大不大（用一个参数来指定的）
        ，如果特别大，直接进入old区（FGC才会结束），
        如果不够大，会进入TLAB（线程本地分配），到Eden区，进行GC(这个GC可以是FGC，也可以是YGC)清除，
        如果清完了结束；如果没有清完进S1,S1在进行GC的清除，
        如果年龄够了进入Old区，如果不够进S2.
    
    6.Object o= new Object()在内存中占用多个字节？
        16
        
    7. Hotspot开启内存压缩的规则（64位机）
        4G以下：直接砍掉高32位
        4G-32G：开启classPointers 、OOPS压缩
        32G以上：压缩无效
        
        使用64位机，并不是内存越大越好
    
    8.IdentityHashCode的问题
        
        对象头(Markworde)什么时候会产生HashCode?  调用未重写HashCode方法或System.identityHashCode()；重写过的hashcode方法计算的结果不会存在这里
        
        如果对象没有重写HashCode方法，默认是调用os::random产生hashcode，可以通过System.identityHashCode获取
        
        当一个对象计算过IdentityHashCode之后，不能进入偏向锁状态
        
        当一个对象处于偏向锁状态时，并且需要计算IdentityhashCode时，偏向锁会被撤销，并且锁会膨胀为重量级锁
        
    9.使用JavaAgent测试Object的大小
        JavaAgent代理机制，class文件loading到内存中，首先需要经过Agent代理，Agent代理可以知道对象的大小，这个Agent需要自己实现
        
        
    
### 五、JMM
    JMM:(java memory model)java内存模型
    1.硬件层面的数据一致性
        总线锁
            锁L3 cache;效率低
        缓存锁（使用一致性协议）
            缓存一致性协议有：MESI、MSI、MOSI
            inter采用MESI协议，大多数人用的是inter的cpu
            
            Modified:我修改过了
            Exclusive(排它的)：只有我在用
            Shared：我读，别人也在读
            Invalid（无效的）：我读的时候，别人改过了
        
    2.基本概念
        1、存储器的层次结构
            L0(寄存器)、L1、L2
            L3、L4(主存)、L5(磁盘)、L6(远程文件存储)
        2、缓存行cache line   64bytes   
        
        3、缓存行对齐 cacheline padding  提高效率
            代码验证
        
            应用在：1.Disruptor
                2.LinkedTransferQueue
        4、WCBuffer(WriteCombliningBuffer)合并写   4bytes
            比L1 cache还快
        
    3.乱序问题
        读指令
        写指令：因为WCBuffer合并写缓存，所以写指令也会出现执行重排
        
        指令重排
        必须使用Memory barrier(内存屏障)
        
        美团程序，验证指令重排
        
    4.保证特定情况下不乱序
        1.硬件层面
            硬件CPU的内存屏障：lFence  sFence  mFence
            硬件级别的lock汇编指令：x86的"lock..."原子指令
        2.JVM级别规范：JSR-133
            JVM的屏障依赖CPU的内存屏障
            JVM只是规范，具体的实现由CPU厂商决定
            
            loadloadBarrier
            loadStoreBarrier
            storeStoreBarrier
            storeloadBarrier
            
            还有happen-before原则、as if serial原则（不管如何重排序，单线程执行结果不会改变）
                
    5.volatile底层细节
         1. 字节码层面
            字节码指令：ACC_VOLATILE  0x0040
       
        2. JVM层面
           volatile内存区的读写 都加屏障
           JVM的内存屏障是依赖CPU的内存屏障的
        
           StoreStoreBarrier
           volatile 写操作
           StoreLoadBarrier
        
           LoadLoadBarrier
           volatile 读操作
           LoadStoreBarrier
           
        3. OS和硬件层面
            windows lock 指令实现 | MESI实现    
            lock指令 xxx执行  xxx指令的时候保证对内存区域加锁
        
    6.synchronized底层细节
        1. 字节码层面
           方法层面：ACC_SYNCHRONIZED 0x0020
           同步语句块：monitorenter monitorexit
        
        2. JVM层面
           C C++ 调用了操作系统提供的同步机制
           
        3. OS和硬件层面
           X86 : lock cmpxchg / xxx

### 六、JavaRuntimeDataArea & InstructionSet
    java运行时数据区
        Direct Memory
            jvm可以直接访问内核空间（OS管理的的内存）
            jdk1.4以后增加NIO，提高效率，实现zero copy
            
        线程私有：
            程序计数器(PC)
            native method stacks(NMS)
            JVM stacks(VMS)
                栈帧Frame，每个方法对应一个栈帧
                栈帧包含的内容：
                    local variable Table 局部变量表
                    Operand stack操作数栈
                    dynamic linking动态链接
                    return address返回地址
            
        线程共享：
            method area
                runtime constant pool
                
                1.面试题：永久代和元数据区的区别：
                    方法区属于逻辑概念，永久代和元数据区是具体实现
                    永久代Perm space：
                        <1.8
                        字符串常量位于永久代
                        不受堆内存管理
                        FGC不会清理
                        大小启动必须制定，并且不能变
                    Meta space：
                        >=1.8
                        字符串常量位于堆内存
                        会触发FGC
                        不设定的话，最大就是物理内存
                    
                
            Heap
            
    指令集
        1.从二进制指令来理解++i 和i++
        
            解析：int i=8; i=i++;
            查看二进制码指令
                 0 bipush 8  8压栈
                 2 istore_1  出栈，并赋值给局部变量表i，i=8
                 3 iload_1 i=8压栈
                 4 iinc 1 by 1  局部变量表中的i加1，i=9（i++是在局部变量表中完成的）
                 7 istore_1  栈中i(i=8)出栈,并赋值给局部变量表中的i，这时i=8 
                 8 getstatic #2 <java/lang/System.out>
                11 iload_1  i压栈(i=8)
                12 invokevirtual #3 <java/io/PrintStream.println> 调用println方法(非静态方法)
                15 return
            
        
            解析：int i=8; i=++i;
            查看二进制码指令
                 0 bipush 8  8压栈
                 2 istore_1  出栈，并赋值给局部变量表i（i=8）
                 3 iinc 1 by 1  局部变量表中的i加1，i=9（++i是在局部变量表中完成的）
                 6 iload_1   i=9压栈
                 7 istore_1   i=9出栈
                 8 getstatic #2 <java/lang/System.out>
                11 iload_1   i=9压栈
                12 invokevirtual #3 <java/io/PrintStream.println>
                15 return
                
        2.查看代码中的指令（建议熟读并明白每一行的意思）
            常见代码
            new对象（重点，理解指令重排的基础）
            有返回值
            递归
            invokeXXX
            
        3.常用指令：
            <clinit> 类的静态语句块
            <init> 构造方法
            store
            load
            pop
            mul
            sub
            invoke
            
            1. InvokeStatic  调静态方法
            2. InvokeVirtual  调普通非静态方法，该命令自带多态
                final方法  普通非静态方法
            3. InvokeInterface
            4. InovkeSpecial
               可以直接定位，不需要多态的方法
               private方法 ， 构造方法
            5. InvokeDynamic
               JVM最难的指令
               lambda表达式或者反射或者其他动态语言（scala kotlin，或者CGLib 或ASM），动态产生的class，会用到的指令
        
                会产生一个lambda表达式的匿名内部类
        4.面试题：
            for(;;){
                I i=C::n;
            }
            这段代码会产生什么问题？
            
            分析：死循环，因为lambda表达会产生匿名内部类，匿名内部类会放在method Area中，
                JDK1.8之前，是Perm space,  FGC不会清理，并造成OOM
                JDK1.8之后，是MetaSpace，FGC会清理，触发FGC，不会造成OOM；【但是如果FGC以后，内存空间还不够，会造成OOM】
            
            答案：  
                JDK1.8之前，是Perm space,  FGC不会清理，并造成OOM
                JDK1.8之后，是MetaSpace，FGC会清理，触发FGC，不会造成OOM；【但是如果FGC以后，内存空间还不够，会造成OOM】
                        
                        
            java Visual VM查看JVM内存空间的工具
```
代码1： public class Hello_01 {
    public void m4() {
        Object o = new Object();
    }
}   

二进制的指令；
m4
    0 new #2 <java/lang/Object>   新建一个对象
    3 dup  对象指针复制
    4 invokespecial #1 <java/lang/Object.<init>>  执行Object的构造方法
    7 astore_1  出栈，对象指针赋值给o
    8 return

    new  new对象
    dup  new对象后，对象地址会压栈；dup复制该对象地址
    invokespecial <init>  现在有两个对象地址，执行构造方法后会弹出dup的对象地址，剩下一个对象地址；
        执行完构造方法，会把上面dup的对象地址弹出去，这时候对象才算初始化完成
        这时候栈里剩下的对象地址，指向了初始化后的对象
    astore_1  把初始化的对象地址指向h对象
    
    ==这块可以理解指令重排的问题，双重检查装载单例模式，volatile的原因
```

                
```
public class Hello_02 {
    public static void main(String[] args) {
        Hello_02 h = new Hello_02();
        h.m1();
    }

    public void m1() {
        int i = 200;
    }

}

二进制指令分析
main
     0 new #2 <com/mashibing/jvm/c4_RuntimeDataAreaAndInstructionSet/Hello_02>  新建对象，成员变量赋默认值
     3 dup
     4 invokespecial #3 <com/mashibing/jvm/c4_RuntimeDataAreaAndInstructionSet/Hello_02.<init>>  调用构造方法，成员变量赋初始值
     7 astore_1  出栈，对象指针赋给h
     8 aload_1  h压栈
     9 invokevirtual #4 <com/mashibing/jvm/c4_RuntimeDataAreaAndInstructionSet/Hello_02.m1> 调用m1方法
    12 return
    
m1
    0 sipush 200
    3 istore_1
    4 return

```

==简历可以写：熟悉GC常用算法，熟悉常见垃圾收集器、具有实际JVM调优实战经验==

### 七、GC调优基础知识
    1.什么是垃圾：没有任何引用指向的一个对象或多个对象
    2.如何定位垃圾：引用计数（ReferenceCount）、根可达算法（RootSearching）
        什么是根对象（GC Roots）：当一个程序马上启动的时候需要的对象就是根对象
            线程栈变量、静态变量、常量池、JNI指针
            
    3.常见的垃圾回收算法
        mark-sweep
        copying
        mark-compact
        分代垃圾回收算法
        
    4.JVM堆内存分代模型（用于分代垃圾回收算法）
        新生代+老年代+方法区（永久代/元数据）
        
        S1->S2分代年龄设置：-XX:MaxTenuringThreshold
        
        除Epsilon  Shenandoah  ZGC以外都使用逻辑分代
        G1逻辑分代，物理不分代
        其他的不仅逻辑分代，物理也分代
        
        面试题：永久代和元数据的区别
        
        新生代：Eden + 2 Suvibor
            算法：copying
            -Xmn
            
        老年代：
            算法：mark-sweep或mark-compact
            -Xms  -Xmx
            
        jvm1.5 新生代：老年代=1:3
        jvm1.8 新生代：老年代=1:2
        查询命令：java -XX:+PrintFlagsFinal -version | grep NewRatio
        
        尽量减少FGC
        MinorGC = YGC
        MajorGC = FGC
        
    5.对象分配过程
        栈上分配
        线程本地分配TLAB
        Eden-S1-S2
        Old
        
    6.对象如何进入老年代
        1.设置GC次数  -XX:MaxTenuringThreshold
            CMS 6
            G1 15
            Paraller Scavenge  15
        2.动态年龄
            Eden+S0  超过S2的50%
            年龄最大的进入old区
        3.分配担保
            YGC时，Survivor区空间不够，通过空间担保直接进入老年代
            
    7.常见的垃圾回收期
        Serial（几十兆）:串行回收
        Serial Old
        
        Paraller Scavenge（上百兆 - 几个G） ：并行回收
        Paraller Old
        
        ParNew：并发回收
        CMS（20G）：并发回收、STW=200ms
            算法：三色标记 + Incremental Update（增量更新）
        
        G1（上百G，10ms）：三色标记 + SATB
        
        ZGC（1ms）：ColoredPointers颜色指针 + LoadBarrier读屏障
        Epsilon
        Shenandoah：ColoredPointers颜色指针 + WriteBarrier写屏障
        
    8.垃圾收集器跟内存大小的关系
         1. Serial 几十兆
         2. PS 上百兆 - 几个G
         3. CMS - 20G
         4. G1 - 上百G
         5. ZGC - 4T - 16T（JDK13）
        
    9.CMS阶段
        初始标记：
        预整理：Card Marking
        并发标记:
        重新标记:STW,时间不长
        并发整理：浮动垃圾
        后期整理
        
    10.CMS的问题：
        1. Memory Fragmentation(内存碎片化) 内存碎片化，比较严重
            解决方案：对碎片进行压缩
             -XX:+UseCMSCompactAtFullCollection
             -XX:CMSFullGCsBeforeCompaction 默认为0 指的是经过多少次FGC才进行压缩
         
        2.Floating Garbage 浮动垃圾
            解决方案：降低触发CMS的阈值
             –XX:CMSInitiatingOccupancyFraction 92%(1.8以后改为)
             可以降低这个值（可以降低到80%），让CMS保持老年代足够的空间
    
        
        
        
        